vllm_npu/__init__.py
vllm_npu/config.py
vllm_npu/npu_adaptor.py
vllm_npu/utils.py
vllm_npu/attention/__init__.py
vllm_npu/attention/backends.py
vllm_npu/attention/selector.py
vllm_npu/core/__init__.py
vllm_npu/engine/__init__.py
vllm_npu/engine/ascend_engine.py
vllm_npu/engine/async_ascend_engine.py
vllm_npu/executor/__init__.py
vllm_npu/executor/ascend_executor.py
vllm_npu/executor/ascend_ray_executor.py
vllm_npu/executor/ray_utils.py
vllm_npu/model_executor/__init__.py
vllm_npu/model_executor/ascend_model_loader.py
vllm_npu/model_executor/layers/__init__.py
vllm_npu/model_executor/layers/ascend_sampler.py
vllm_npu/model_executor/models/__init__.py
vllm_npu/model_executor/models/ascend/__init__.py
vllm_npu/model_executor/models/ascend/mindie_llm_wrapper.py
vllm_npu/usage/__init__.py
vllm_npu/usage/usage_lib.py
vllm_npu/worker/__init__.py
vllm_npu/worker/ascend_model_runner.py
vllm_npu/worker/ascend_worker.py
vllm_npu/worker/cache_engine.py
npu_vllm-0.4.2.post3.dist-info/METADATA
npu_vllm-0.4.2.post3.dist-info/WHEEL
npu_vllm-0.4.2.post3.dist-info/top_level.txt
npu_vllm-0.4.2.post3.dist-info/RECORD
